pypangraph/__init__.py
pypangraph/block_branching.py
pypangraph/blockpairs_analysis.py
pypangraph/logger.py
pypangraph/pangraph_alignments.py
pypangraph/pangraph_interface.py
pypangraph/pangraph_locator.py
pypangraph/pangraph_projector.py
pypangraph/pangraph_utils.py
pypangraph/pangraph_visualize.py
pypangraph/pangraph_wrapper.py
pypangraph/visualization_projection.py
pypangraph/msu/__init__.py
pypangraph/msu/msu.py
pypangraph/msu/msu_utils.py
pypangraph-0.1.3.dist-info/LICENSE
pypangraph-0.1.3.dist-info/METADATA
pypangraph-0.1.3.dist-info/WHEEL
pypangraph-0.1.3.dist-info/top_level.txt
pypangraph-0.1.3.dist-info/RECORD
