Metadata-Version: 2.1
Name: pypangraph
Version: 0.1.3
Summary: package to manipulate pangenomes produced by PanGraph
Author-email: Marco Molari <mmolari91@gmail.com>
Project-URL: Homepage, https://github.com/mmolari/pypangraph
Project-URL: Issues, https://github.com/mmolari/pypangraph/issues
Classifier: Programming Language :: Python :: 3
Classifier: License :: OSI Approved :: MIT License
Classifier: Operating System :: OS Independent
Requires-Python: >=3.9
License-File: LICENSE
Requires-Dist: matplotlib
Requires-Dist: numpy
Requires-Dist: pandas
Requires-Dist: biopython
Requires-Dist: scipy
Requires-Dist: networkx
